mainmod.v
module inc_cond_mppt (
    input wire clk,
    input wire reset,
    input wire start,
    input wire [15:0] voltage_in,
    input wire [15:0] current_in,
    output reg [15:0] duty_cycle,
    output reg mpp_found,
    output reg [15:0] power_out
);

    // Parameters
    parameter DUTY_STEP = 16'h0040; // 0.25 in 8.8 format
    parameter DELTA_V = 16'h0008;   // Minimum voltage change
    parameter MAX_DUTY = 16'h3FFF;  // Maximum duty cycle
    parameter MIN_DUTY = 16'h0001;  // Minimum duty cycle
    
    // Internal registers
    reg [15:0] v_prev, i_prev, p_prev;
    reg [15:0] dv, di, conductance, inc_conductance;
    reg [31:0] power_calc;
    reg [1:0] state;
    
    // State definitions
    localparam IDLE = 2'b00;
    localparam CALCULATE = 2'b01;
    localparam UPDATE = 2'b10;
    
    // Power calculation
    always @* begin
        power_calc = voltage_in * current_in; // 32-bit result
        power_out = power_calc[23:8]; // Scale down to 16-bit
    end
    
    // Main algorithm FSM
    always @(posedge clk or posedge reset) begin
        if (reset) begin
            state <= IDLE;
            v_prev <= 16'h0000;
            i_prev <= 16'h0000;
            p_prev <= 16'h0000;
            duty_cycle <= 16'h2000; // Start at 50% duty
            mpp_found <= 1'b0;
        end else begin
            case (state)
                IDLE: begin
                    if (start) begin
                        v_prev <= voltage_in;
                        i_prev <= current_in;
                        p_prev <= power_out;
                        state <= CALCULATE;
                    end
                end
                
                CALCULATE: begin
                    // Calculate differences
                    dv = voltage_in - v_prev;
                    di = current_in - i_prev;
                    
                    // Avoid division by implementing comparison directly
                    if (dv == 0) begin
                        if (di == 0) begin
                            // Operating point unchanged
                            mpp_found <= 1'b1;
                        end else begin
                            // Change duty based on current change
                            if (di > 0) begin
                                duty_cycle <= (duty_cycle < MAX_DUTY) ? 
                                             duty_cycle + DUTY_STEP : MAX_DUTY;
                            end else begin
                                duty_cycle <= (duty_cycle > MIN_DUTY) ? 
                                             duty_cycle - DUTY_STEP : MIN_DUTY;
                            end
                            mpp_found <= 1'b0;
                        end
                    end else begin
                        // Calculate conductances using fixed-point approximation
                        // Simple comparison without division
                        if (di == 0) begin
                            // No current change
                            mpp_found <= 1'b1;
                        end else if ((di > 0 && dv > 0) || (di < 0 && dv < 0)) begin
                            // Left of MPP - increase voltage
                            duty_cycle <= (duty_cycle < MAX_DUTY) ? 
                                         duty_cycle + DUTY_STEP : MAX_DUTY;
                            mpp_found <= 1'b0;
                        end else begin
                            // Right of MPP - decrease voltage
                            duty_cycle <= (duty_cycle > MIN_DUTY) ? 
                                         duty_cycle - DUTY_STEP : MIN_DUTY;
                            mpp_found <= 1'b0;
                        end
                    end
                    
                    state <= UPDATE;
                end
                
                UPDATE: begin
                    // Store current values as previous for next iteration
                    v_prev <= voltage_in;
                    i_prev <= current_in;
                    p_prev <= power_out;
                    state <= IDLE;
                end
            endcase
        end
    end

endmodule

mainmod_tb.v
`timescale 1ns/1ps
`include "mainmod.v"

module tb_inc_cond_mppt;

    // Testbench signals
    reg clk, reset, start;
    reg [15:0] voltage_in, current_in;
    wire [15:0] duty_cycle, power_out;
    wire mpp_found;
    
    // Clock generation
    always #5 clk = ~clk; // 100MHz clock
    
    // Instantiate DUT - Make sure this matches your actual module name
    // If your module is called "inc_cond_mppt", keep this
    // If it's called something else, change it here
    inc_cond_mppt dut (
        .clk(clk),
        .reset(reset),
        .start(start),
        .voltage_in(voltage_in),
        .current_in(current_in),
        .duty_cycle(duty_cycle),
        .mpp_found(mpp_found),
        .power_out(power_out)
    );
    
    // Solar panel characteristic simulation
    reg [15:0] irradiance;
    reg [15:0] temperature;
    reg [15:0] simulated_current;
    
    // Power Monitoring Variables
    real total_power;
    integer sample_count;
    integer cycle_count;
    real average_power;
    real max_power;
    real min_power;
    
    // Environmental condition tracking
    reg [7:0] condition_id;
    reg [127:0] condition_name; // Changed from string to reg for iverilog compatibility
    
    // Task to simulate solar panel
    task simulate_solar_panel;
        input [15:0] v_sim;
        output [15:0] i_sim;
        reg [31:0] i_calc;
        begin
            // Simplified solar panel I-V characteristic
            if (v_sim < 16'h2000) begin // Below 32V
                i_calc = 16'h0C00 - ((v_sim * 16'h0040) >> 8); // Linear region
            end else begin
                // Quadratic drop near Voc
                i_calc = 16'h0800 - (((v_sim - 16'h2000) * (v_sim - 16'h2000)) >> 10);
            end
            
            // Apply irradiance and temperature effects
            i_calc = (i_calc * irradiance) >> 12;
            
            // Temperature effect (simplified)
            if (temperature > 16'h0C80) begin // Above 25°C
                i_calc = i_calc - ((temperature - 16'h0C80) >> 4);
            end
            
            i_sim = (i_calc > 0) ? i_calc[15:0] : 16'h0000;
        end
    endtask
    
    // Function to convert fixed-point to real
    function real fixed_to_real;
        input [15:0] fixed_value;
        real result;
        begin
            result = fixed_value;
            result = result / 256.0; // Q8.8 to real
            fixed_to_real = result;
        end
    endfunction
    
    // Power monitoring task
    task monitor_power;
        input [127:0] condition;
        input integer duration_cycles;
        real current_power_real;
        real power_ripple;
        real tracking_efficiency;
        real theoretical_max;
        begin
            $display("\n=== Starting Power Monitoring: %s ===", condition);
            $display("Time: %0t ns", $time);
            
            // Reset power statistics for this condition
            total_power = 0.0;
            sample_count = 0;
            max_power = 0.0;
            min_power = 999999.0;
            
            // Monitor for specified duration
            repeat (duration_cycles) begin
                @(posedge clk);
                #1; // Wait a bit after clock edge
                
                if (!reset) begin
                    // Update power statistics
                    current_power_real = fixed_to_real(power_out);
                    
                    total_power = total_power + current_power_real;
                    sample_count = sample_count + 1;
                    
                    if (current_power_real > max_power) 
                        max_power = current_power_real;
                    if (current_power_real < min_power && current_power_real > 0) 
                        min_power = current_power_real;
                end
            end
            
            // Calculate and display results
            if (sample_count > 0) begin
                average_power = total_power / sample_count;
                power_ripple = max_power - min_power;
                theoretical_max = fixed_to_real(16'h0C00) * fixed_to_real(16'h2000) * fixed_to_real(irradiance);
                tracking_efficiency = (average_power / theoretical_max) * 100.0;
                
                $display("=== Power Statistics: %s ===", condition);
                $display("Monitoring Duration: %0d cycles", duration_cycles);
                $display("Samples Collected: %0d", sample_count);
                $display("Average Power: %.2f W", average_power);
                $display("Maximum Power: %.2f W", max_power);
                $display("Minimum Power: %.2f W", min_power);
                $display("Power Ripple: %.2f W (%.1f%%)", 
                         power_ripple, 
                         (power_ripple / average_power) * 100.0);
                $display("Theoretical Max Power: %.2f W", theoretical_max);
                $display("Tracking Efficiency: %.1f%%", tracking_efficiency);
                $display("=================================\n");
            end
        end
    endtask
    
    // Change environmental condition
    task change_condition;
        input [15:0] new_irradiance;
        input [15:0] new_temperature;
        input [7:0] new_condition_id;
        input [127:0] new_condition_name;
        begin
            $display("\n*** Changing Condition to: %s ***", new_condition_name);
            $display("Old Irradiance: %h (%.2f sun)", irradiance, fixed_to_real(irradiance));
            $display("New Irradiance: %h (%.2f sun)", new_irradiance, fixed_to_real(new_irradiance));
            $display("Old Temperature: %h (%.1f °C)", temperature, fixed_to_real(temperature));
            $display("New Temperature: %h (%.1f °C)", new_temperature, fixed_to_real(new_temperature));
            
            irradiance = new_irradiance;
            temperature = new_temperature;
            condition_id = new_condition_id;
            condition_name = new_condition_name;
            
            // Allow some time for transition
            #1000;
        end
    endtask
    
    // Main test sequence
    integer i;
    reg [15:0] simulated_voltage;
    
    initial begin
        // Initialize signals
        clk = 0;
        reset = 1;
        start = 0;
        voltage_in = 16'h0000;
        current_in = 16'h0000;
        irradiance = 16'h1000; // 1.0 sun
        temperature = 16'h0C80; // 25°C
        condition_id = 0;
        condition_name = "Initial";
        
        // Initialize power monitoring
        total_power = 0.0;
        sample_count = 0;
        average_power = 0.0;
        max_power = 0.0;
        min_power = 999999.0;
        cycle_count = 0;
        
        // Reset sequence
        #100;
        reset = 0;
        #10;
        start = 1;
        
        $display("========== MPPT SIMULATION STARTED ==========");
        $display("Initial Conditions: 1.0 sun, 25°C");
        $display("============================================\n");
        
        // Test Case 1: Standard Conditions (1.0 sun, 25°C)
        change_condition(16'h1000, 16'h0C80, 1, "Standard Conditions");
        monitor_power("Standard Conditions (1.0 sun, 25°C)", 500);
        
        // Test Case 2: Reduced Irradiance (0.7 sun)
        change_condition(16'h0B00, 16'h0C80, 2, "Reduced Irradiance");
        monitor_power("Reduced Irradiance (0.7 sun, 25°C)", 500);
        
        // Test Case 3: Partial Shading (0.4 sun)
        change_condition(16'h0660, 16'h0C80, 3, "Partial Shading");
        monitor_power("Partial Shading (0.4 sun, 25°C)", 500);
        
        // Test Case 4: High Temperature (45°C)
        change_condition(16'h1000, 16'h1680, 4, "High Temperature");
        monitor_power("High Temperature (1.0 sun, 45°C)", 500);
        
        // Test Case 5: Low Irradiance + High Temperature
        change_condition(16'h0800, 16'h1680, 5, "Cloudy & Hot");
        monitor_power("Cloudy & Hot (0.5 sun, 45°C)", 500);
        
        // Test Case 6: Return to Standard
        change_condition(16'h1000, 16'h0C80, 6, "Return to Standard");
        monitor_power("Return to Standard Conditions", 500);
        
        // Final Summary
        $display("\n========== SIMULATION COMPLETED ==========");
        $display("Total Simulation Time: %0t ns", $time);
        $display("Total Clock Cycles: %0d", cycle_count);
        $display("==========================================\n");
        
        $finish;
    end
    
    // Cycle counter
    always @(posedge clk) begin
        if (reset) begin
            cycle_count <= 0;
        end else begin
            cycle_count <= cycle_count + 1;
        end
    end
    
    // Main simulation loop
    always @(posedge clk) begin
        if (!reset && start) begin
            // Simulate solar panel response based on duty cycle
            simulated_voltage = (duty_cycle * 16'h0040) >> 8;
            simulate_solar_panel(simulated_voltage, simulated_current);
            
            voltage_in = simulated_voltage;
            current_in = simulated_current;
            
            // Display occasional status
            if (cycle_count % 200 == 0) begin
                $display("Cycle: %4d | Condition: %s | Duty: %4h (%.1f%%) | V: %.1fV | I: %.1fA | P: %.1fW | MPP: %b",
                        cycle_count, condition_name, duty_cycle, 
                        (fixed_to_real(duty_cycle) / 256.0) * 100.0,
                        fixed_to_real(voltage_in),
                        fixed_to_real(current_in),
                        fixed_to_real(power_out),
                        mpp_found);
            end
        end
    end
    
    // Real-time power display every MPP found
    always @(posedge mpp_found) begin
        if (!reset) begin
            $display("MPP Found! Cycle: %d | Power: %.1fW | Condition: %s", 
                    cycle_count, fixed_to_real(power_out), condition_name);
        end
    end
    
    // File output for waveform analysis
    initial begin
        $dumpfile("inc_cond_mppt.vcd");
        $dumpvars(0, tb_inc_cond_mppt);
    end

endmodule

inc_cond_mppt.vcd
$date
	Fri Oct 03 14:29:28 2025
$end
$version
	Icarus Verilog
$end
$timescale
	1ps
$end
$scope module tb_inc_cond_mppt $end
$var wire 16 ! power_out [15:0] $end
$var wire 1 " mpp_found $end
$var wire 16 # duty_cycle [15:0] $end
$var reg 1 $ clk $end
$var reg 8 % condition_id [7:0] $end
$var reg 128 & condition_name [127:0] $end
$var reg 16 ' current_in [15:0] $end
$var reg 16 ( irradiance [15:0] $end
$var reg 1 ) reset $end
$var reg 16 * simulated_current [15:0] $end
$var reg 16 + simulated_voltage [15:0] $end
$var reg 1 , start $end
$var reg 16 - temperature [15:0] $end
$var reg 16 . voltage_in [15:0] $end
$var real 1 / average_power $end
$var integer 32 0 cycle_count [31:0] $end
$var real 1 1 max_power $end
$var real 1 2 min_power $end
$var integer 32 3 sample_count [31:0] $end
$var real 1 4 total_power $end
$scope function fixed_to_real $end
$var reg 16 5 fixed_value [15:0] $end
$var real 1 6 result $end
$upscope $end
$scope module dut $end
$var wire 1 $ clk $end
$var wire 16 7 current_in [15:0] $end
$var wire 1 ) reset $end
$var wire 1 , start $end
$var wire 16 8 voltage_in [15:0] $end
$var reg 16 9 di [15:0] $end
$var reg 16 : duty_cycle [15:0] $end
$var reg 16 ; dv [15:0] $end
$var reg 16 < i_prev [15:0] $end
$var reg 1 " mpp_found $end
$var reg 16 = p_prev [15:0] $end
$var reg 32 > power_calc [31:0] $end
$var reg 16 ? power_out [15:0] $end
$var reg 2 @ state [1:0] $end
$var reg 16 A v_prev [15:0] $end
$upscope $end
$scope task change_condition $end
$var reg 8 B new_condition_id [7:0] $end
$var reg 128 C new_condition_name [127:0] $end
$var reg 16 D new_irradiance [15:0] $end
$var reg 16 E new_temperature [15:0] $end
$upscope $end
$scope task monitor_power $end
$var reg 128 F condition [127:0] $end
$var real 1 G current_power_real $end
$var integer 32 H duration_cycles [31:0] $end
$var real 1 I power_ripple $end
$var real 1 J theoretical_max $end
$var real 1 K tracking_efficiency $end
$upscope $end
$scope task simulate_solar_panel $end
$var reg 32 L i_calc [31:0] $end
$var reg 16 M i_sim [15:0] $end
$var reg 16 N v_sim [15:0] $end
$upscope $end
$upscope $end
$enddefinitions $end
#0
$dumpvars
bx N
bx M
bx L
r0 K
r0 J
r0 I
bx H
r0 G
bx F
bx E
bx D
bx C
bx B
b0 A
b0 @
b0 ?
b0 >
b0 =
b0 <
bx ;
b10000000000000 :
bx 9
b0 8
b0 7
r0 6
bx 5
r0 4
b0 3
r999999 2
r0 1
b0 0
r0 /
b0 .
b110010000000 -
0,
bx +
bx *
1)
b1000000000000 (
b0 '
b1001001011011100110100101110100011010010110000101101100 &
b0 %
0$
b10000000000000 #
0"
b0 !
$end
#5000
1$
#10000
0$
#15000
1$
#20000
0$
#25000
1$
#30000
0$
#35000
1$
#40000
0$
#45000
1$
#50000
0$
#55000
1$
#60000
0$
#65000
1$
#70000
0$
#75000
1$
#80000
0$
#85000
1$
#90000
0$
#95000
1$
#100000
0$
0)
#105000
b1 0
1$
#110000
0$
b1101110011001000110000101110010011001000010000001000011011011110110111001100100011010010111010001101001011011110110111001110011 &
b1 %
r12.5 6
b110010000000 5
b1101110011001000110000101110010011001000010000001000011011011110110111001100100011010010111010001101001011011110110111001110011 C
b1 B
b110010000000 E
b1000000000000 D
1,
#115000
b1 @
b110000000000 <
b10 0
b110000000000 '
b110000000000 7
b110000000000 *
b110000000000 M
b110000000000 L
b0 N
b0 +
1$
#120000
0$
#125000
r0 6
b0 5
b10 @
1"
b11 0
b0 9
b0 ;
1$
#130000
0$
#135000
b0 @
b100 0
1$
#140000
0$
#145000
b1 @
b101 0
1$
#150000
0$
#155000
b10 @
b110 0
1$
#160000
0$
#165000
b0 @
b111 0
1$
#170000
0$
#175000
b1 @
b1000 0
1$
#180000
0$
#185000
b10 @
b1001 0
1$
#190000
0$
#195000
b0 @
b1010 0
1$
#200000
0$
#205000
b1 @
b1011 0
1$
#210000
0$
#215000
b10 @
b1100 0
1$
#220000
0$
#225000
b0 @
b1101 0
1$
#230000
0$
#235000
b1 @
b1110 0
1$
#240000
0$
#245000
b10 @
b1111 0
1$
#250000
0$
#255000
b0 @
b10000 0
1$
#260000
0$
#265000
b1 @
b10001 0
1$
#270000
0$
#275000
b10 @
b10010 0
1$
#280000
0$
#285000
b0 @
b10011 0
1$
#290000
0$
#295000
b1 @
b10100 0
1$
#300000
0$
#305000
b10 @
b10101 0
1$
#310000
0$
#315000
b0 @
b10110 0
1$
#320000
0$
#325000
b1 @
b10111 0
1$
#330000
0$
#335000
b10 @
b11000 0
1$
#340000
0$
#345000
b0 @
b11001 0
1$
#350000
0$
#355000
b1 @
b11010 0
1$
#360000
0$
#365000
b10 @
b11011 0
1$
#370000
0$
#375000
b0 @
b11100 0
1$
#380000
0$
#385000
b1 @
b11101 0
1$
#390000
0$
#395000
b10 @
b11110 0
1$
#400000
0$
#405000
b0 @
b11111 0
1$
#410000
0$
#415000
b1 @
b100000 0
1$
#420000
0$
#425000
b10 @
b100001 0
1$
#430000
0$
#435000
b0 @
b100010 0
1$
#440000
0$
#445000
b1 @
b100011 0
1$
#450000
0$
#455000
b10 @
b100100 0
1$
#460000
0$
#465000
b0 @
b100101 0
1$
#470000
0$
#475000
b1 @
b100110 0
1$
#480000
0$
#485000
b10 @
b100111 0
1$
#490000
0$
#495000
b0 @
b101000 0
1$
#500000
0$
#505000
b1 @
b101001 0
1$
#510000
0$
#515000
b10 @
b101010 0
1$
#520000
0$
#525000
b0 @
b101011 0
1$
#530000
0$
#535000
b1 @
b101100 0
1$
#540000
0$
#545000
b10 @
b101101 0
1$
#550000
0$
#555000
b0 @
b101110 0
1$
#560000
0$
#565000
b1 @
b101111 0
1$
#570000
0$
#575000
b10 @
b110000 0
1$
#580000
0$
#585000
b0 @
b110001 0
1$
#590000
0$
#595000
b1 @
b110010 0
1$
#600000
0$
#605000
b10 @
b110011 0
1$
#610000
0$
#615000
b0 @
b110100 0
1$
#620000
0$
#625000
b1 @
b110101 0
1$
#630000
0$
#635000
b10 @
b110110 0
1$
#640000
0$
#645000
b0 @
b110111 0
1$
#650000
0$
#655000
b1 @
b111000 0
1$
#660000
0$
#665000
b10 @
b111001 0
1$
#670000
0$
#675000
b0 @
b111010 0
1$
#680000
0$
#685000
b1 @
b111011 0
1$
#690000
0$
#695000
b10 @
b111100 0
1$
#700000
0$
#705000
b0 @
b111101 0
1$
#710000
0$
#715000
b1 @
b111110 0
1$
#720000
0$
#725000
b10 @
b111111 0
1$
#730000
0$
#735000
b0 @
b1000000 0
1$
#740000
0$
#745000
b1 @
b1000001 0
1$
#750000
0$
#755000
b10 @
b1000010 0
1$
#760000
0$
#765000
b0 @
b1000011 0
1$
#770000
0$
#775000
b1 @
b1000100 0
1$
#780000
0$
#785000
b10 @
b1000101 0
1$
#790000
0$
#795000
b0 @
b1000110 0
1$
#800000
0$
#805000
b1 @
b1000111 0
1$
#810000
0$
#815000
b10 @
b1001000 0
1$
#820000
0$
#825000
b0 @
b1001001 0
1$
#830000
0$
#835000
b1 @
b1001010 0
1$
#840000
0$
#845000
b10 @
b1001011 0
1$
#850000
0$
#855000
b0 @
b1001100 0
1$
#860000
0$
#865000
b1 @
b1001101 0
1$
#870000
0$
#875000
b10 @
b1001110 0
1$
#880000
0$
#885000
b0 @
b1001111 0
1$
#890000
0$
#895000
b1 @
b1010000 0
1$
#900000
0$
#905000
b10 @
b1010001 0
1$
#910000
0$
#915000
b0 @
b1010010 0
1$
#920000
0$
#925000
b1 @
b1010011 0
1$
#930000
0$
#935000
b10 @
b1010100 0
1$
#940000
0$
#945000
b0 @
b1010101 0
1$
#950000
0$
#955000
b1 @
b1010110 0
1$
#960000
0$
#965000
b10 @
b1010111 0
1$
#970000
0$
#975000
b0 @
b1011000 0
1$
#980000
0$
#985000
b1 @
b1011001 0
1$
#990000
0$
#995000
b10 @
b1011010 0
1$
#1000000
0$
#1005000
b0 @
b1011011 0
1$
#1010000
0$
#1015000
b1 @
b1011100 0
1$
#1020000
0$
#1025000
b10 @
b1011101 0
1$
#1030000
0$
#1035000
b0 @
b1011110 0
1$
#1040000
0$
#1045000
b1 @
b1011111 0
1$
#1050000
0$
#1055000
b10 @
b1100000 0
1$
#1060000
0$
#1065000
b0 @
b1100001 0
1$
#1070000
0$
#1075000
b1 @
b1100010 0
1$
#1080000
0$
#1085000
b10 @
b1100011 0
1$
#1090000
0$
#1095000
b0 @
b1100100 0
1$
#1100000
0$
#1105000
b1 @
b1100101 0
1$
#1110000
0$
b111110100 H
b101000001100010010111000110000001000000111001101110101011011100010110000100000001100100011010111000010101100000100001100101001 F
#1115000
b10 @
b1100110 0
1$
#1116000
b1 3
#1120000
0$
#1125000
b0 @
b1100111 0
1$
#1126000
b10 3
#1130000
0$
#1135000
b1 @
b1101000 0
1$
#1136000
b11 3
#1140000
0$
#1145000
b10 @
b1101001 0
1$
#1146000
b100 3
#1150000
0$
#1155000
b0 @
b1101010 0
1$
#1156000
b101 3
#1160000
0$
#1165000
b1 @
b1101011 0
1$
#1166000
b110 3
#1170000
0$
#1175000
b10 @
b1101100 0
1$
#1176000
b111 3
#1180000
0$
#1185000
b0 @
b1101101 0
1$
#1186000
b1000 3
#1190000
0$
#1195000
b1 @
b1101110 0
1$
#1196000
b1001 3
#1200000
0$
#1205000
b10 @
b1101111 0
1$
#1206000
b1010 3
#1210000
0$
#1215000
b0 @
b1110000 0
1$
#1216000
b1011 3
#1220000
0$
#1225000
b1 @
b1110001 0
1$
#1226000
b1100 3
#1230000
0$
#1235000
b10 @
b1110010 0
1$
#1236000
b1101 3
#1240000
0$
#1245000
b0 @
b1110011 0
1$
#1246000
b1110 3
#1250000
0$
#1255000
b1 @
b1110100 0
1$
#1256000
b1111 3
#1260000
0$
#1265000
b10 @
b1110101 0
1$
#1266000
b10000 3
#1270000
0$
#1275000
b0 @
b1110110 0
1$
#1276000
b10001 3
#1280000
0$
#1285000
b1 @
b1110111 0
1$
#1286000
b10010 3
#1290000
0$
#1295000
b10 @
b1111000 0
1$
#1296000
b10011 3
#1300000
0$
#1305000
b0 @
b1111001 0
1$
#1306000
b10100 3
#1310000
0$
#1315000
b1 @
b1111010 0
1$
#1316000
b10101 3
#1320000
0$
#1325000
b10 @
b1111011 0
1$
#1326000
b10110 3
#1330000
0$
#1335000
b0 @
b1111100 0
1$
#1336000
b10111 3
#1340000
0$
#1345000
b1 @
b1111101 0
1$
#1346000
b11000 3
#1350000
0$
#1355000
b10 @
b1111110 0
1$
#1356000
b11001 3
#1360000
0$
#1365000
b0 @
b1111111 0
1$
#1366000
b11010 3
#1370000
0$
#1375000
b1 @
b10000000 0
1$
#1376000
b11011 3
#1380000
0$
#1385000
b10 @
b10000001 0
1$
#1386000
b11100 3
#1390000
0$
#1395000
b0 @
b10000010 0
1$
#1396000
b11101 3
#1400000
0$
#1405000
b1 @
b10000011 0
1$
#1406000
b11110 3
#1410000
0$
#1415000
b10 @
b10000100 0
1$
#1416000
b11111 3
#1420000
0$
#1425000
b0 @
b10000101 0
1$
#1426000
b100000 3
#1430000
0$
#1435000
b1 @
b10000110 0
1$
#1436000
b100001 3
#1440000
0$
#1445000
b10 @
b10000111 0
1$
#1446000
b100010 3
#1450000
0$
#1455000
b0 @
b10001000 0
1$
#1456000
b100011 3
#1460000
0$
#1465000
b1 @
b10001001 0
1$
#1466000
b100100 3
#1470000
0$
#1475000
b10 @
b10001010 0
1$
#1476000
b100101 3
#1480000
0$
#1485000
b0 @
b10001011 0
1$
#1486000
b100110 3
#1490000
0$
#1495000
b1 @
b10001100 0
1$
#1496000
b100111 3
#1500000
0$
#1505000
b10 @
b10001101 0
1$
#1506000
b101000 3
#1510000
0$
#1515000
b0 @
b10001110 0
1$
#1516000
b101001 3
#1520000
0$
#1525000
b1 @
b10001111 0
1$
#1526000
b101010 3
#1530000
0$
#1535000
b10 @
b10010000 0
1$
#1536000
b101011 3
#1540000
0$
#1545000
b0 @
b10010001 0
1$
#1546000
b101100 3
#1550000
0$
#1555000
b1 @
b10010010 0
1$
#1556000
b101101 3
#1560000
0$
#1565000
b10 @
b10010011 0
1$
#1566000
b101110 3
#1570000
0$
#1575000
b0 @
b10010100 0
1$
#1576000
b101111 3
#1580000
0$
#1585000
b1 @
b10010101 0
1$
#1586000
b110000 3
#1590000
0$
#1595000
b10 @
b10010110 0
1$
#1596000
b110001 3
#1600000
0$
#1605000
b0 @
b10010111 0
1$
#1606000
b110010 3
#1610000
0$
#1615000
b1 @
b10011000 0
1$
#1616000
b110011 3
#1620000
0$
#1625000
b10 @
b10011001 0
1$
#1626000
b110100 3
#1630000
0$
#1635000
b0 @
b10011010 0
1$
#1636000
b110101 3
#1640000
0$
#1645000
b1 @
b10011011 0
1$
#1646000
b110110 3
#1650000
0$
#1655000
b10 @
b10011100 0
1$
#1656000
b110111 3
#1660000
0$
#1665000
b0 @
b10011101 0
1$
#1666000
b111000 3
#1670000
0$
#1675000
b1 @
b10011110 0
1$
#1676000
b111001 3
#1680000
0$
#1685000
b10 @
b10011111 0
1$
#1686000
b111010 3
#1690000
0$
#1695000
b0 @
b10100000 0
1$
#1696000
b111011 3
#1700000
0$
#1705000
b1 @
b10100001 0
1$
#1706000
b111100 3
#1710000
0$
#1715000
b10 @
b10100010 0
1$
#1716000
b111101 3
#1720000
0$
#1725000
b0 @
b10100011 0
1$
#1726000
b111110 3
#1730000
0$
#1735000
b1 @
b10100100 0
1$
#1736000
b111111 3
#1740000
0$
#1745000
b10 @
b10100101 0
1$
#1746000
b1000000 3
#1750000
0$
#1755000
b0 @
b10100110 0
1$
#1756000
b1000001 3
#1760000
0$
#1765000
b1 @
b10100111 0
1$
#1766000
b1000010 3
#1770000
0$
#1775000
b10 @
b10101000 0
1$
#1776000
b1000011 3
#1780000
0$
#1785000
b0 @
b10101001 0
1$
#1786000
b1000100 3
#1790000
0$
#1795000
b1 @
b10101010 0
1$
#1796000
b1000101 3
#1800000
0$
#1805000
b10 @
b10101011 0
1$
#1806000
b1000110 3
#1810000
0$
#1815000
b0 @
b10101100 0
1$
#1816000
b1000111 3
#1820000
0$
#1825000
b1 @
b10101101 0
1$
#1826000
b1001000 3
#1830000
0$
#1835000
b10 @
b10101110 0
1$
#1836000
b1001001 3
#1840000
0$
#1845000
b0 @
b10101111 0
1$
#1846000
b1001010 3
#1850000
0$
#1855000
b1 @
b10110000 0
1$
#1856000
b1001011 3
#1860000
0$
#1865000
b10 @
b10110001 0
1$
#1866000
b1001100 3
#1870000
0$
#1875000
b0 @
b10110010 0
1$
#1876000
b1001101 3
#1880000
0$
#1885000
b1 @
b10110011 0
1$
#1886000
b1001110 3
#1890000
0$
#1895000
b10 @
b10110100 0
1$
#1896000
b1001111 3
#1900000
0$
#1905000
b0 @
b10110101 0
1$
#1906000
b1010000 3
#1910000
0$
#1915000
b1 @
b10110110 0
1$
#1916000
b1010001 3
#1920000
0$
#1925000
b10 @
b10110111 0
1$
#1926000
b1010010 3
#1930000
0$
#1935000
b0 @
b10111000 0
1$
#1936000
b1010011 3
#1940000
0$
#1945000
b1 @
b10111001 0
1$
#1946000
b1010100 3
#1950000
0$
#1955000
b10 @
b10111010 0
1$
#1956000
b1010101 3
#1960000
0$
#1965000
b0 @
b10111011 0
1$
#1966000
b1010110 3
#1970000
0$
#1975000
b1 @
b10111100 0
1$
#1976000
b1010111 3
#1980000
0$
#1985000
b10 @
b10111101 0
1$
#1986000
b1011000 3
#1990000
0$
#1995000
b0 @
b10111110 0
1$
#1996000
b1011001 3
#2000000
0$
#2005000
b1 @
b10111111 0
1$
#2006000
b1011010 3
#2010000
0$
#2015000
b10 @
b11000000 0
1$
#2016000
b1011011 3
#2020000
0$
#2025000
b0 @
b11000001 0
1$
#2026000
b1011100 3
#2030000
0$
#2035000
b1 @
b11000010 0
1$
#2036000
b1011101 3
#2040000
0$
#2045000
b10 @
b11000011 0
1$
#2046000
b1011110 3
#2050000
0$
#2055000
b0 @
b11000100 0
1$
#2056000
b1011111 3
#2060000
0$
#2065000
b1 @
b11000101 0
1$
#2066000
b1100000 3
#2070000
0$
#2075000
b10 @
b11000110 0
1$
#2076000
b1100001 3
#2080000
0$
#2085000
b0 @
b11000111 0
1$
#2086000
b1100010 3
#2090000
0$
#2095000
b1 @
b11001000 0
1$
#2096000
b1100011 3
#2100000
0$
#2105000
b10 @
b11001001 0
r0 6
b0 5
1$
#2106000
b1100100 3
#2110000
0$
#2115000
b0 @
b11001010 0
1$
#2116000
b1100101 3
#2120000
0$
#2125000
b1 @
b11001011 0
1$
#2126000
b1100110 3
#2130000
0$
#2135000
b10 @
b11001100 0
1$
#2136000
b1100111 3
#2140000
0$
#2145000
b0 @
b11001101 0
1$
#2146000
b1101000 3
#2150000
0$
#2155000
b1 @
b11001110 0
1$
#2156000
b1101001 3
#2160000
0$
#2165000
b10 @
b11001111 0
1$
#2166000
b1101010 3
#2170000
0$
#2175000
b0 @
b11010000 0
1$
#2176000
b1101011 3
#2180000
0$
#2185000
b1 @
b11010001 0
1$
#2186000
b1101100 3
#2190000
0$
#2195000
b10 @
b11010010 0
1$
#2196000
b1101101 3
#2200000
0$
#2205000
b0 @
b11010011 0
1$
#2206000
b1101110 3
#2210000
0$
#2215000
b1 @
b11010100 0
1$
#2216000
b1101111 3
#2220000
0$
#2225000
b10 @
b11010101 0
1$
#2226000
b1110000 3
#2230000
0$
#2235000
b0 @
b11010110 0
1$
#2236000
b1110001 3
#2240000
0$
#2245000
b1 @
b11010111 0
1$
#2246000
b1110010 3
#2250000
0$
#2255000
b10 @
b11011000 0
1$
#2256000
b1110011 3
#2260000
0$
#2265000
b0 @
b11011001 0
1$
#2266000
b1110100 3
#2270000
0$
#2275000
b1 @
b11011010 0
1$
#2276000
b1110101 3
#2280000
0$
#2285000
b10 @
b11011011 0
1$
#2286000
b1110110 3
#2290000
0$
#2295000
b0 @
b11011100 0
1$
#2296000
b1110111 3
#2300000
0$
#2305000
b1 @
b11011101 0
1$
#2306000
b1111000 3
#2310000
0$
#2315000
b10 @
b11011110 0
1$
#2316000
b1111001 3
#2320000
0$
#2325000
b0 @
b11011111 0
1$
#2326000
b1111010 3
#2330000
0$
#2335000
b1 @
b11100000 0
1$
#2336000
b1111011 3
#2340000
0$
#2345000
b10 @
b11100001 0
1$
#2346000
b1111100 3
#2350000
0$
#2355000
b0 @
b11100010 0
1$
#2356000
b1111101 3
#2360000
0$
#2365000
b1 @
b11100011 0
1$
#2366000
b1111110 3
#2370000
0$
#2375000
b10 @
b11100100 0
1$
#2376000
b1111111 3
#2380000
0$
#2385000
b0 @
b11100101 0
1$
#2386000
b10000000 3
#2390000
0$
#2395000
b1 @
b11100110 0
1$
#2396000
b10000001 3
#2400000
0$
#2405000
b10 @
b11100111 0
1$
#2406000
b10000010 3
#2410000
0$
#2415000
b0 @
b11101000 0
1$
#2416000
b10000011 3
#2420000
0$
#2425000
b1 @
b11101001 0
1$
#2426000
b10000100 3
#2430000
0$
#2435000
b10 @
b11101010 0
1$
#2436000
b10000101 3
#2440000
0$
#2445000
b0 @
b11101011 0
1$
#2446000
b10000110 3
#2450000
0$
#2455000
b1 @
b11101100 0
1$
#2456000
b10000111 3
#2460000
0$
#2465000
b10 @
b11101101 0
1$
#2466000
b10001000 3
#2470000
0$
#2475000
b0 @
b11101110 0
1$
#2476000
b10001001 3
